simple_monads/__init__.py
simple_monads/maybe.py
simple_monads/py.typed
simple_monads/result.py
simple_py_monads-0.0.5.dist-info/LICENSE
simple_py_monads-0.0.5.dist-info/WHEEL
simple_py_monads-0.0.5.dist-info/METADATA
simple_py_monads-0.0.5.dist-info/RECORD
